mig/__init__.py
mig/io/__init__.py
mig/io/_async_io.py
mig/io/_io.py
mig_utils-0.1.7.4.dist-info/METADATA
mig_utils-0.1.7.4.dist-info/WHEEL
mig_utils-0.1.7.4.dist-info/top_level.txt
mig_utils-0.1.7.4.dist-info/RECORD
