Metadata-Version: 1.0
Name: mig-utils
Version: 0.1.7.4
Summary: Minimum Intrusion Grid (MiG) Utilities library
Home-page: https://github.com/rasmunk/mig_utils
Author: Rasmus Munk
Author-email: munk1@live.dk
License: UNKNOWN
Platform: UNKNOWN
